[
    {
      
      "name": "Project X",
      "description": "An innovative project that leverages cutting-edge technologies.",
      "start_date": "2022-03-01",
      "end_date": "2022-09-30",
      "status": "In Progress"
    },
    {
      
      "name": "CyberSec Guardian",
      "description": "A cybersecurity project aimed at securing digital assets.",      
      "start_date": "2022-05-15",
      "end_date": "2022-12-31",
      "status": "Planning"
    },
    {
      
      "name": "CloudOps Accelerator",
      "description": "Optimizing cloud operations for improved efficiency.",      
      "start_date": "2022-04-10",
      "end_date": "2022-11-15",
      "status": "Completed"
    },
    {
      
      "name": "AI Chatbot Integration",
      "description": "Integrating an AI-driven chatbot for customer support.",     
      "start_date": "2022-06-20",
      "end_date": "2023-02-28",
      "status": "In Progress"
    },
    {
      
      "name": "Blockchain Solutions",
      "description": "Developing blockchain solutions for secure transactions.",    
      "start_date": "2022-07-05",
      "end_date": "2023-05-31",
      "status": "Planning"
    },
    {
        
        "name": "DataHub Integration",
        "description": "Integrating a centralized data hub for seamless data management.",       
        "start_date": "2022-08-10",
        "end_date": "2023-03-31",
        "status": "In Progress"
      },
      {
        
        "name": "IoT Smart Home Platform",
        "description": "Building a smart home platform using Internet of Things (IoT) technology.",       
        "start_date": "2022-09-15",
        "end_date": "2023-06-30",
        "status": "Planning"
      },
      {
        
        "name": "DevOps Transformation",
        "description": "Implementing DevOps practices to enhance development and operations collaboration.",        
        "start_date": "2022-10-05",
        "end_date": "2023-04-30",
        "status": "In Progress"
      },
      {
        
        "name": "Augmented Reality App",
        "description": "Developing an augmented reality app for immersive user experiences.",        
        "start_date": "2022-11-20",
        "end_date": "2023-08-15",
        "status": "Planning"
      },
      {
        
        "name": "Machine Learning Fraud Detection",
        "description": "Implementing machine learning algorithms for fraud detection in financial transactions.",        
        "start_date": "2022-12-01",
        "end_date": "2023-10-31",
        "status": "In Progress"
      },
      {
        
        "name": "E-commerce Platform Upgrade",
        "description": "Upgrading the existing e-commerce platform with new features and improved performance.",       
        "start_date": "2023-01-15",
        "end_date": "2023-08-31",
        "status": "Planning"
      },
      {
        
        "name": "Mobile App Security Assessment",
        "description": "Conducting a comprehensive security assessment for a mobile application.",        
        "start_date": "2023-02-10",
        "end_date": "2023-05-30",
        "status": "In Progress"
      },
      {
        
        "name": "Robotic Process Automation Implementation",
        "description": "Implementing robotic process automation to streamline repetitive business processes.",    
        "start_date": "2023-03-05",
        "end_date": "2023-12-15",
        "status": "Planning"
      },
      {
        
        "name": "Cloud Migration Strategy",
        "description": "Developing a comprehensive strategy for migrating IT infrastructure to the cloud.",       
        "start_date": "2023-04-20",
        "end_date": "2024-01-31",
        "status": "In Progress"
      },
      {
        
        "name": "Virtual Reality Training Platform",
        "description": "Creating a virtual reality platform for immersive employee training experiences.",       
        "start_date": "2023-05-01",
        "end_date": "2023-10-30",
        "status": "Planning"
      },
      {
        
        "name": "Big Data Analytics Dashboard",
        "description": "Developing a dashboard for analyzing and visualizing big data analytics results.",       
        "start_date": "2023-06-15",
        "end_date": "2024-03-31",
        "status": "In Progress"
      },
      {
        
        "name": "Cybersecurity Training Platform",
        "description": "Building an interactive platform for cybersecurity training and simulations.",       
        "start_date": "2023-07-10",
        "end_date": "2023-11-30",
        "status": "Planning"
      },
      {
        
        "name": "Blockchain Integration for Supply Chain",
        "description": "Integrating blockchain technology to enhance transparency in the supply chain.",        
        "start_date": "2023-08-05",
        "end_date": "2024-06-30",
        "status": "In Progress"
      },
      {
        
        "name": "AI-driven Customer Support Chatbot",
        "description": "Developing an AI-driven chatbot for efficient and personalized customer support.",
        "start_date": "2023-09-20",
        "end_date": "2024-02-28",
        "status": "Plannin"
      }
  ]
  